flask_antijs.py
Flask_AntiJs-0.0.1.dist-info/LICENSE
Flask_AntiJs-0.0.1.dist-info/METADATA
Flask_AntiJs-0.0.1.dist-info/WHEEL
Flask_AntiJs-0.0.1.dist-info/top_level.txt
Flask_AntiJs-0.0.1.dist-info/RECORD
